lona_html5_qrcode/__init__.py
lona_html5_qrcode/html/__init__.py
lona_html5_qrcode/html/html5_qrcode_scanner.py
lona_html5_qrcode/static/lona-html5-qrcode/themes.css
lona_html5_qrcode/static/lona-html5-qrcode/widgets.js
lona_html5_qrcode/static/lona-html5-qrcode/dist/LICENSE
lona_html5_qrcode/static/lona-html5-qrcode/dist/html5-qrcode.min.js
lona_html5_qrcode-0.1.dist-info/LICENSE.txt
lona_html5_qrcode-0.1.dist-info/METADATA
lona_html5_qrcode-0.1.dist-info/WHEEL
lona_html5_qrcode-0.1.dist-info/top_level.txt
lona_html5_qrcode-0.1.dist-info/RECORD
