Metadata-Version: 2.1
Name: lona-html5-qrcode
Version: 0.1
Summary: Html5-QRCode bindings for Lona
Author-email: Florian Scherf <mail@florianscherf.de>
License: MIT License
Project-URL: Homepage, https://github.com/lona-web-org/lona-html5-qrcode
Project-URL: Repository, https://github.com/lona-web-org/lona-html5-qrcode
Project-URL: Bug Tracker, https://github.com/lona-web-org/lona-html5-qrcode/issues
Classifier: Development Status :: 4 - Beta
Classifier: License :: OSI Approved :: MIT License
Classifier: Natural Language :: English
Classifier: Programming Language :: Python :: 3 :: Only
Classifier: Topic :: Internet :: WWW/HTTP
Classifier: Topic :: Internet :: WWW/HTTP :: Dynamic Content
Requires-Python: >=3.7
License-File: LICENSE.txt
Requires-Dist: lona (>=1.12.1)
Provides-Extra: dev
Requires-Dist: lona-picocss ; extra == 'dev'
Provides-Extra: packaging
Requires-Dist: build ; extra == 'packaging'
Requires-Dist: twine ; extra == 'packaging'
